pipindex/__init__.py
pipindex/command.py
pipindex/exceptions.py
pipindex/models.py
pipindex/utils.py
pipindex-0.1.3.dist-info/LICENSE
pipindex-0.1.3.dist-info/METADATA
pipindex-0.1.3.dist-info/WHEEL
pipindex-0.1.3.dist-info/entry_points.txt
pipindex-0.1.3.dist-info/top_level.txt
pipindex-0.1.3.dist-info/RECORD
