Metadata-Version: 2.1
Name: pipindex
Version: 0.1.3
Summary: pipindex creates PEP-503 compliant package repositories.
Home-page: https://github.com/Oneflow-Inc/pipindex
Author: ci-bot
Author-email: ci-bot@oneflow.org
License: MIT
Platform: UNKNOWN
Classifier: Development Status :: 3 - Alpha
Classifier: Intended Audience :: Developers
Classifier: Intended Audience :: Information Technology
Classifier: Intended Audience :: System Administrators
Classifier: Topic :: Software Development :: Build Tools
Classifier: Topic :: System :: Systems Administration
Classifier: License :: OSI Approved :: MIT License
Classifier: Programming Language :: Python :: 2.7
Classifier: Programming Language :: Python :: 3.5
Classifier: Programming Language :: Python :: 3.6
License-File: LICENSE
Requires-Dist: pip (>=8)
Provides-Extra: dev
Requires-Dist: flake8 ; extra == 'dev'
Requires-Dist: pytest ; extra == 'dev'
Requires-Dist: pytest-cov ; extra == 'dev'
Requires-Dist: moto ; extra == 'dev'
